magoptlib/__init__.py
magoptlib/load_text.py
magoptlib/magoptlib.py
magoptlib/transformation.py
magoptlib/visualization.py
magoptlib-0.1.0.dist-info/LICENSE
magoptlib-0.1.0.dist-info/METADATA
magoptlib-0.1.0.dist-info/WHEEL
magoptlib-0.1.0.dist-info/RECORD
