Metadata-Version: 2.1
Name: magoptlib
Version: 0.1.0
Summary: Global spherical harmonic analysis for optimal magnet positioning.
License: MIT
Author: Palma Inczeffy
Requires-Python: >=3.11
Classifier: License :: OSI Approved :: MIT License
Classifier: Programming Language :: Python :: 3
Classifier: Programming Language :: Python :: 3.11
Classifier: Programming Language :: Python :: 3.12
Requires-Dist: matplotlib (>=3.7)
Requires-Dist: numpy (>=1.26.0,<2.0.0)
Requires-Dist: scikit-learn (>=1.5.1,<2.0.0)
Requires-Dist: scipy (>=1.13.0)
